Metadata-Version: 1.1
Name: torch-unique
Version: 1.0.3
Summary: Optimized PyTorch Unique Operation
Home-page: https://github.com/rusty1s/pytorch_unique
Author: Matthias Fey
Author-email: matthias.fey@tu-dortmund.de
License: UNKNOWN
Download-URL: https://github.com/rusty1s/pytorch_unique/archive/1.0.3.tar.gz
Keywords: pytorch,unique,python
Platform: UNKNOWN
